AUTHOR
LICENSE
MANIFEST.in
README.rst
setup.cfg
setup.py
doc/source/_static/pyconnectome.png
doc/source/_static/carousel/altas3.png
doc/source/_static/carousel/connectome_forward_2.00mm.png
doc/source/_static/carousel/network_heatmap.png
pyConnectome.egg-info/PKG-INFO
pyConnectome.egg-info/SOURCES.txt
pyConnectome.egg-info/dependency_links.txt
pyConnectome.egg-info/requires.txt
pyConnectome.egg-info/top_level.txt
pyconnectome/__init__.py
pyconnectome/configuration.py
pyconnectome/exceptions.py
pyconnectome/info.py
pyconnectome/wrapper.py
pyconnectome/connectomes/__init__.py
pyconnectome/connectomes/complete.py
pyconnectome/connectomes/reduced.py
pyconnectome/metrics/__init__.py
pyconnectome/metrics/dfold.py
pyconnectome/metrics/schcc.py
pyconnectome/models/__init__.py
pyconnectome/models/deconvolution.py
pyconnectome/models/noddi.py
pyconnectome/models/shm.py
pyconnectome/models/shore.py
pyconnectome/models/tensor.py
pyconnectome/plotting/__init__.py
pyconnectome/plotting/animate.py
pyconnectome/plotting/colors.py
pyconnectome/plotting/fold.py
pyconnectome/plotting/network.py
pyconnectome/plotting/pvtk.py
pyconnectome/plotting/pvtk_show_labels.py
pyconnectome/plotting/scenes.py
pyconnectome/plotting/slicer.py
pyconnectome/plotting/tractography.py
pyconnectome/scripts/pyconnectome_ants_register
pyconnectome/scripts/pyconnectome_ants_template
pyconnectome/scripts/pyconnectome_bedpostx
pyconnectome/scripts/pyconnectome_compress_tractogram
pyconnectome/scripts/pyconnectome_life
pyconnectome/scripts/pyconnectome_metrics
pyconnectome/scripts/pyconnectome_metrics_heatmap
pyconnectome/scripts/pyconnectome_mitk_tractogram
pyconnectome/scripts/pyconnectome_mrtrix_tractogram
pyconnectome/scripts/pyconnectome_probtrackx2_complete
pyconnectome/scripts/pyconnectome_probtrackx2_tractogram
pyconnectome/scripts/pyconnectome_reduced_connectome
pyconnectome/scripts/pyconnectome_reduced_probtrackx2
pyconnectome/scripts/pyconnectome_register
pyconnectome/scripts/pyconnectome_report_tractogram
pyconnectome/scripts/pyconnectome_tissue_segmentation
pyconnectome/tests/tests_models/test_deconvolution.py
pyconnectome/tests/tests_models/test_tensor.py
