Metadata-Version: 2.1
Name: pyConnectome
Version: 1.0.1
Summary: 
